Workbook
Name ListaBancos: TABELA!$C$8:$C$57
Name ListaBens: TABELA!$G$8:$G$14
Name ListaContas: TABELA!$D$8:$D$16
Name ListaDespesas: TABELA!$F$8:$F$17
Name ListaDocumentos: TABELA!$H$8:$H$14
Name ListaRendimentos: TABELA!$E$8:$E$18

Sheet INÍCIO
N25: 0 | P25: Progresso | Q25: Restante
P26: =IFERROR(COUNTIF(DOCUMENTOS!F14:F51,"SIM")/COUNTA(DOCUMENTOS!C14:C51),0) -> 0.8 | Q26: =1-P26 -> 0.2
B45: =SUM(RENDIMENTOS!G:G) -> 27006.3 | F45: Desenvolvido por Camila Ribeiro Pinto
B46: =COUNTA(BANCOS!D13,BANCOS!D26,BANCOS!D39) -> 3 | F46: LinkedIn | G46: | | H46: GitHub
B47: =COUNTIF(DOCUMENTOS!F14:F51,"SIM") -> 8 | F47: IR Organiza • Projeto de portfólio
B48: =COUNTIF(DOCUMENTOS!H14:H51,"PENDENTE")+COUNTIF(DOCUMENTOS!H14:H51,"INCOMPLETO") -> 2

Sheet TITULAR
C3: 1. DADOS PESSOAIS
C4: Cadastre os dados do titular e dos dependentes para organizar sua declaração.
C6: NOME COMPLETO | D6: LARISSA MONTEIRO ALBUQUERQUE
C7: CPF | D7: 12312312398
C8: DATA DE NASCIMENTO | D8: 34605
C9: TÍTULO DE ELEITOR | D9: 31713388
C10: ESTADO CIVIL | D10: Casado(a)
C11: NOME DO CÔNJUGE | D11: RAFAELA DUARTE ALBUQUERQUE
C13: ENDEREÇO
C15: LOGRADOURO | D15: Rua das Acácias
C16: NÚMERO | D16: 245
C17: COMPLEMENTO | D17: Apto 804, Bloco B
C18: BAIRRO | D18: Casa Forte
C19: MUNICÍPIO | D19: Recife
C20: UF | D20: PE
C21: CEP | D21: 987654321
C23: CONTATO
C25: TELEFONE | D25: 8131713388
C26: CELULAR | D26: 81931713388
C27: E-MAIL | D27: larissa@example.com
C29: INFORMAÇÕES DA DECLARAÇÃO
C31: DECLARAÇÃO ANTERIOR? | D31: SIM
C32: HOUVE ALTERAÇÃO CADASTRAL? | D32: NÃO
C33: CÔNJUGE É DEPENDENTE? | D33: NÃO
C34: RESIDENTE NO EXTERIOR? | D34: NÃO
C35: POSSUI DEPENDENTES? | D35: SIM
C37: CADASTRO DE DEPENDENTES
C38: NOME COMPLETO | D38: HELENA MONTEIRO ALBUQUERQUE
C39: CPF | D39: 32112312398
C40: DATA DE NASCIMENTO | D40: 45563
C41: VÍNCULO | D41: Filho(a)
C42: OBSERVAÇÕES | D42: Nenhuma

Sheet BANCOS
C3: 2. CONTAS E INFORMES BANCÁRIOS
C4: Registre suas contas bancárias, saldos e informes de rendimentos.
F7: =SUM(D19,D32,D45) -> 25971.35
C12: 1º Banco
C13: BANCO | D13: 336 - C6 Bank
C14: TIPO DE CONTA/APLICAÇÃO | D14: Conta corrente
C15: AGÊNCIA | D15: 1
C16: CONTA | D16: 123456789
C17: ANO-CALENDÁRIO | D17: 2025
C18: SALDO DO ANO ANTERIOR | D18: 2850
C19: SALDO DO ANO-CALENDÁRIO | D19: 5430.75
C20: INFORME RECEBIDO? | D20: SIM
C21: SITUAÇÃO | D21: =IF(OR(D13="",D14="",D15="",D16="",D17="",D18="",D19="",D20=""),"INCOMPLETO",IF(D20="SIM","CONCLUÍDO","PENDENTE")) -> CONCLUÍDO
C22: COMPROVANTE 🖇️ | D22: informe_c6_2025.pdf
C23: OBSERVAÇÕES | D23: Dados conferidos
C25: 1º Banco
C26: BANCO | D26: 77 - Banco Inter
C27: TIPO DE CONTA/APLICAÇÃO | D27: Conta poupança
C28: AGÊNCIA | D28: 1
C29: CONTA | D29: 45678901-2
C30: ANO-CALENDÁRIO | D30: 2025
C31: SALDO DO ANO ANTERIOR | D31: 4500
C32: SALDO DO ANO-CALENDÁRIO | D32: 7890.2
C33: INFORME RECEBIDO?
C34: SITUAÇÃO | D34: =IF(OR(D26="",D27="",D28="",D29="",D30="",D31="",D32="",D33=""),"INCOMPLETO",IF(D33="SIM","CONCLUÍDO","PENDENTE")) -> INCOMPLETO
C35: COMPROVANTE 🖇️
C36: OBSERVAÇÕES | D36: Aguardando informe bancário
C38: 1º Banco
C39: BANCO | D39: 33 - Banco Santander
C40: TIPO DE CONTA/APLICAÇÃO | D40: Conta corrente
C41: AGÊNCIA | D41: 1234
C42: CONTA | D42: 987654321
C43: ANO-CALENDÁRIO | D43: 2025
C44: SALDO DO ANO ANTERIOR | D44: 8200
C45: SALDO DO ANO-CALENDÁRIO | D45: 12650.4
C46: INFORME RECEBIDO? | D46: NÃO
C47: SITUAÇÃO | D47: =IF(OR(D39="",D40="",D41="",D42="",D43="",D44="",D45="",D46=""),"INCOMPLETO",IF(D46="SIM","CONCLUÍDO","PENDENTE")) -> PENDENTE
C48: COMPROVANTE 🖇️
C49: OBSERVAÇÕES | D49: Aguardando informe bancário

Sheet RENDIMENTOS
C3: 3. CONTROLE DE RENDIMENTOS | J3: =SUM(G:G) -> 27006.3
C4: Registre e organize seus rendimentos para a declaração do Imposto de Renda. | J4: =SUM(H:H) -> 2250
J5: =COUNTIF(I:I,"PENDENTE")+COUNTIF(I:I,"INCOMPLETO") -> 1
C12: ENTRADAS
C13: DATA | D13: FONTE PAGADORA | E13: CPF/CNPJ | F13: TIPO DE RENDIMENTO | G13: VALOR RECEBIDO | H13: IMPOSTO RETIDO | I13: SITUAÇÃO
C14: 45662 | D14: Horizonte Tecnologia Ltda. | E14: 12345678900 | F14: Salário | G14: 4500 | H14: 450 | I14: =IF(COUNTA(C14:H14)=0,"",IF(OR(C14="",D14="",E14="",F14="",G14="",H14=""),"INCOMPLETO","CONCLUÍDO")) -> CONCLUÍDO
C15: 45663 | D15: Horizonte Tecnologia Ltda. | E15: 23456789000 | F15: Salário | G15: 4500 | H15: 450 | I15: =IF(COUNTA(C15:H15)=0,"",IF(OR(C15="",D15="",E15="",F15="",G15="",H15=""),"INCOMPLETO","CONCLUÍDO")) -> CONCLUÍDO
C16: 45664 | D16: Horizonte Tecnologia Ltda. | E16: 34567890100 | F16: Salário | G16: 4500 | H16: 450 | I16: =IF(COUNTA(C16:H16)=0,"",IF(OR(C16="",D16="",E16="",F16="",G16="",H16=""),"INCOMPLETO","CONCLUÍDO")) -> CONCLUÍDO
C17: 45665 | D17: Pessoa física fictícia | E17: 45678901200 | F17: Aluguel | G17: 1800 | H17: 0 | I17: =IF(COUNTA(C17:H17)=0,"",IF(OR(C17="",D17="",E17="",F17="",G17="",H17=""),"INCOMPLETO","CONCLUÍDO")) -> CONCLUÍDO
C18: 45666 | D18: Cliente Exemplo Ltda. | E18: 56789012300 | F18: Trabalho autônomo | G18: 2200 | H18: 0 | I18: =IF(COUNTA(C18:H18)=0,"",IF(OR(C18="",D18="",E18="",F18="",G18="",H18=""),"INCOMPLETO","CONCLUÍDO")) -> CONCLUÍDO
C19: 45667 | D19: Banco Exemplo | E19: 67890123400 | F19: Juros de aplicações | G19: 180.5 | H19: 0 | I19: =IF(COUNTA(C19:H19)=0,"",IF(OR(C19="",D19="",E19="",F19="",G19="",H19=""),"INCOMPLETO","CONCLUÍDO")) -> CONCLUÍDO
C20: 45668 | D20: Banco Exemplo | E20: 78901234500 | F20: Rendimentos de fundos | G20: 325.8 | H20: 0 | I20: =IF(COUNTA(C20:H20)=0,"",IF(OR(C20="",D20="",E20="",F20="",G20="",H20=""),"INCOMPLETO","CONCLUÍDO")) -> CONCLUÍDO
C21: 45669 | D21: Horizonte Tecnologia Ltda. | E21: 89012345600 | F21: Salário | G21: 4500 | H21: 450 | I21: =IF(COUNTA(C21:H21)=0,"",IF(OR(C21="",D21="",E21="",F21="",G21="",H21=""),"INCOMPLETO","CONCLUÍDO")) -> CONCLUÍDO
C22: 45670 | D22: Horizonte Tecnologia Ltda. | E22: 90123456700 | F22: Salário | G22: 4500 | H22: 450 | I22: =IF(COUNTA(C22:H22)=0,"",IF(OR(C22="",D22="",E22="",F22="",G22="",H22=""),"INCOMPLETO","CONCLUÍDO")) -> CONCLUÍDO
C23: 45671 | D23: Horizonte Tecnologia Ltda. | E23: 11223344500 | F23: 13º salário | I23: =IF(COUNTA(C23:H23)=0,"",IF(OR(C23="",D23="",E23="",F23="",G23="",H23=""),"INCOMPLETO","CONCLUÍDO")) -> INCOMPLETO
I24: =IF(COUNTA(C24:H24)=0,"",IF(OR(C24="",D24="",E24="",F24="",G24="",H24=""),"INCOMPLETO","CONCLUÍDO"))
I25: =IF(COUNTA(C25:H25)=0,"",IF(OR(C25="",D25="",E25="",F25="",G25="",H25=""),"INCOMPLETO","CONCLUÍDO"))
I26: =IF(COUNTA(C26:H26)=0,"",IF(OR(C26="",D26="",E26="",F26="",G26="",H26=""),"INCOMPLETO","CONCLUÍDO"))
I27: =IF(COUNTA(C27:H27)=0,"",IF(OR(C27="",D27="",E27="",F27="",G27="",H27=""),"INCOMPLETO","CONCLUÍDO"))
I28: =IF(COUNTA(C28:H28)=0,"",IF(OR(C28="",D28="",E28="",F28="",G28="",H28=""),"INCOMPLETO","CONCLUÍDO"))
I29: =IF(COUNTA(C29:H29)=0,"",IF(OR(C29="",D29="",E29="",F29="",G29="",H29=""),"INCOMPLETO","CONCLUÍDO"))
I30: =IF(COUNTA(C30:H30)=0,"",IF(OR(C30="",D30="",E30="",F30="",G30="",H30=""),"INCOMPLETO","CONCLUÍDO"))
I31: =IF(COUNTA(C31:H31)=0,"",IF(OR(C31="",D31="",E31="",F31="",G31="",H31=""),"INCOMPLETO","CONCLUÍDO"))
I32: =IF(COUNTA(C32:H32)=0,"",IF(OR(C32="",D32="",E32="",F32="",G32="",H32=""),"INCOMPLETO","CONCLUÍDO"))
I33: =IF(COUNTA(C33:H33)=0,"",IF(OR(C33="",D33="",E33="",F33="",G33="",H33=""),"INCOMPLETO","CONCLUÍDO"))
I34: =IF(COUNTA(C34:H34)=0,"",IF(OR(C34="",D34="",E34="",F34="",G34="",H34=""),"INCOMPLETO","CONCLUÍDO"))
I35: =IF(COUNTA(C35:H35)=0,"",IF(OR(C35="",D35="",E35="",F35="",G35="",H35=""),"INCOMPLETO","CONCLUÍDO"))
... I50: =IF(COUNTA(C50:H50)=0,"",IF(OR(C50="",D50="",E50="",F50="",G50="",H50=""),"INCOMPLETO","CONCLUÍDO"))

Sheet PAGAMENTOS
C3: 4. CONTROLE DE PAGAMENTOS | J3: =SUM(G:G) -> 7570
C4: Organize suas despesas e reembolsos para a declaração do Imposto de Renda. | J4: =SUM(H:H) -> 850
J5: =COUNTIF(I:I,"PENDENTE")+COUNTIF(I:I,"INCOMPLETO") -> 0
C12: SAÍDAS
C13: DATA | D13: PRESTADOR / RECEBEDOR | E13: CPF/CNPJ | F13: TIPO DE DESPESA | G13: VALOR PAGO | H13: VALOR REEMBOLSADO | I13: SITUAÇÃO
C14: 45662 | D14: Clínica Bem-Estar | E14: 12345678900 | F14: Consulta médica | G14: 350 | H14: 0 | I14: =IF(COUNTA(C14:H14)=0,"",IF(OR(C14="",D14="",E14="",F14="",G14="",H14=""),"INCOMPLETO","CONCLUÍDO")) -> CONCLUÍDO
C15: 45669 | D15: Laboratório Vida | E15: 23456789000 | F15: Exames | G15: 420 | H15: 200 | I15: =IF(COUNTA(C15:H15)=0,"",IF(OR(C15="",D15="",E15="",F15="",G15="",H15=""),"INCOMPLETO","CONCLUÍDO")) -> CONCLUÍDO
C16: 45708 | D16: Odonto Saúde | E16: 34567890100 | F16: Dentista | G16: 680 | H16: 0 | I16: =IF(COUNTA(C16:H16)=0,"",IF(OR(C16="",D16="",E16="",F16="",G16="",H16=""),"INCOMPLETO","CONCLUÍDO")) -> CONCLUÍDO
C17: 45721 | D17: Instituto Aprender | E17: 45678901200 | F17: Educação | G17: 1250 | H17: 0 | I17: =IF(COUNTA(C17:H17)=0,"",IF(OR(C17="",D17="",E17="",F17="",G17="",H17=""),"INCOMPLETO","CONCLUÍDO")) -> CONCLUÍDO
C18: 45730 | D18: Clínica Horizonte | E18: 56789012300 | F18: Psicoterapia | G18: 240 | H18: 0 | I18: =IF(COUNTA(C18:H18)=0,"",IF(OR(C18="",D18="",E18="",F18="",G18="",H18=""),"INCOMPLETO","CONCLUÍDO")) -> CONCLUÍDO
C19: 45756 | D19: Hospital Esperança | E19: 67890123400 | F19: Hospital | G19: 1850 | H19: 650 | I19: =IF(COUNTA(C19:H19)=0,"",IF(OR(C19="",D19="",E19="",F19="",G19="",H19=""),"INCOMPLETO","CONCLUÍDO")) -> CONCLUÍDO
C20: 45792 | D20: Saúde Total | E20: 78901234500 | F20: Plano de saúde | G20: 580 | H20: 0 | I20: =IF(COUNTA(C20:H20)=0,"",IF(OR(C20="",D20="",E20="",F20="",G20="",H20=""),"INCOMPLETO","CONCLUÍDO")) -> CONCLUÍDO
C21: 45818 | D21: Instituto Aprender | E21: 89012345600 | F21: Educação | G21: 1250 | H21: 0 | I21: =IF(COUNTA(C21:H21)=0,"",IF(OR(C21="",D21="",E21="",F21="",G21="",H21=""),"INCOMPLETO","CONCLUÍDO")) -> CONCLUÍDO
C22: 45856 | D22: Clínica Bem-Estar | E22: 90123456700 | F22: Consulta médica | G22: 350 | H22: 0 | I22: =IF(COUNTA(C22:H22)=0,"",IF(OR(C22="",D22="",E22="",F22="",G22="",H22=""),"INCOMPLETO","CONCLUÍDO")) -> CONCLUÍDO
C23: 45891 | D23: Previdência Exemplo | E23: 11223344500 | F23: Previdência privada | G23: 600 | H23: 0 | I23: =IF(COUNTA(C23:H23)=0,"",IF(OR(C23="",D23="",E23="",F23="",G23="",H23=""),"INCOMPLETO","CONCLUÍDO")) -> CONCLUÍDO
I24: =IF(COUNTA(C24:H24)=0,"",IF(OR(C24="",D24="",E24="",F24="",G24="",H24=""),"INCOMPLETO","CONCLUÍDO"))
I25: =IF(COUNTA(C25:H25)=0,"",IF(OR(C25="",D25="",E25="",F25="",G25="",H25=""),"INCOMPLETO","CONCLUÍDO"))
I26: =IF(COUNTA(C26:H26)=0,"",IF(OR(C26="",D26="",E26="",F26="",G26="",H26=""),"INCOMPLETO","CONCLUÍDO"))
I27: =IF(COUNTA(C27:H27)=0,"",IF(OR(C27="",D27="",E27="",F27="",G27="",H27=""),"INCOMPLETO","CONCLUÍDO"))
I28: =IF(COUNTA(C28:H28)=0,"",IF(OR(C28="",D28="",E28="",F28="",G28="",H28=""),"INCOMPLETO","CONCLUÍDO"))
I29: =IF(COUNTA(C29:H29)=0,"",IF(OR(C29="",D29="",E29="",F29="",G29="",H29=""),"INCOMPLETO","CONCLUÍDO"))
I30: =IF(COUNTA(C30:H30)=0,"",IF(OR(C30="",D30="",E30="",F30="",G30="",H30=""),"INCOMPLETO","CONCLUÍDO"))
I31: =IF(COUNTA(C31:H31)=0,"",IF(OR(C31="",D31="",E31="",F31="",G31="",H31=""),"INCOMPLETO","CONCLUÍDO"))
I32: =IF(COUNTA(C32:H32)=0,"",IF(OR(C32="",D32="",E32="",F32="",G32="",H32=""),"INCOMPLETO","CONCLUÍDO"))
I33: =IF(COUNTA(C33:H33)=0,"",IF(OR(C33="",D33="",E33="",F33="",G33="",H33=""),"INCOMPLETO","CONCLUÍDO"))
I34: =IF(COUNTA(C34:H34)=0,"",IF(OR(C34="",D34="",E34="",F34="",G34="",H34=""),"INCOMPLETO","CONCLUÍDO"))
I35: =IF(COUNTA(C35:H35)=0,"",IF(OR(C35="",D35="",E35="",F35="",G35="",H35=""),"INCOMPLETO","CONCLUÍDO"))
... I50: =IF(COUNTA(C50:H50)=0,"",IF(OR(C50="",D50="",E50="",F50="",G50="",H50=""),"INCOMPLETO","CONCLUÍDO"))

Sheet BENS E DIREITOS
C3: 5. CONTROLE DE BENS E DIREITOS | J3: =SUM(G:G) -> 250500
C4: Organize seus bens, direitos e valores patrimoniais para a declaração do Imposto de Renda. | J4: =SUM(H:H) -> 249500
J5: =COUNTIF(I:I,"PENDENTE")+COUNTIF(I:I,"INCOMPLETO") -> 1
C12: PATRIMÔNIO
C13: TIPO DE BEM | D13: DESCRIÇÃO | E13: LOCALIZAÇÃO | F13: DATA DE AQUISIÇÃO | G13: VALOR ANTERIOR | H13: VALOR ATUAL | I13: SITUAÇÃO
C14: Imóvel | D14: Apartamento residencial | E14: Recife - PE | F14: 43539 | G14: 180000 | H14: 180000 | I14: =IF(COUNTA(C14:H14)=0,"",IF(OR(C14="",D14="",E14="",F14="",G14="",H14=""),"INCOMPLETO","CONCLUÍDO")) -> CONCLUÍDO
C15: Veículo | D15: Automóvel de passeio | E15: Recife - PE | F15: 44722 | G15: 45000 | H15: 45000 | I15: =IF(COUNTA(C15:H15)=0,"",IF(OR(C15="",D15="",E15="",F15="",G15="",H15=""),"INCOMPLETO","CONCLUÍDO")) -> CONCLUÍDO
C16: Investimento | D16: Aplicação de renda fixa | E16: Banco Exemplo | F16: 44938 | G16: 12000 | H16: 14500 | I16: =IF(COUNTA(C16:H16)=0,"",IF(OR(C16="",D16="",E16="",F16="",G16="",H16=""),"INCOMPLETO","CONCLUÍDO")) -> CONCLUÍDO
C17: Participação societária | D17: Quotas de empresa fictícia | E17: Recife - PE | F17: 44428 | G17: 10000 | H17: 10000 | I17: =IF(COUNTA(C17:H17)=0,"",IF(OR(C17="",D17="",E17="",F17="",G17="",H17=""),"INCOMPLETO","CONCLUÍDO")) -> CONCLUÍDO
C18: Outros bens e direitos | D18: Equipamento de valor relevante | E18: Recife - PE | F18: 45400 | G18: 3500 | I18: =IF(COUNTA(C18:H18)=0,"",IF(OR(C18="",D18="",E18="",F18="",G18="",H18=""),"INCOMPLETO","CONCLUÍDO")) -> INCOMPLETO
I19: =IF(COUNTA(C19:H19)=0,"",IF(OR(C19="",D19="",E19="",F19="",G19="",H19=""),"INCOMPLETO","CONCLUÍDO"))
I20: =IF(COUNTA(C20:H20)=0,"",IF(OR(C20="",D20="",E20="",F20="",G20="",H20=""),"INCOMPLETO","CONCLUÍDO"))
I21: =IF(COUNTA(C21:H21)=0,"",IF(OR(C21="",D21="",E21="",F21="",G21="",H21=""),"INCOMPLETO","CONCLUÍDO"))
I22: =IF(COUNTA(C22:H22)=0,"",IF(OR(C22="",D22="",E22="",F22="",G22="",H22=""),"INCOMPLETO","CONCLUÍDO"))
I23: =IF(COUNTA(C23:H23)=0,"",IF(OR(C23="",D23="",E23="",F23="",G23="",H23=""),"INCOMPLETO","CONCLUÍDO"))
I24: =IF(COUNTA(C24:H24)=0,"",IF(OR(C24="",D24="",E24="",F24="",G24="",H24=""),"INCOMPLETO","CONCLUÍDO"))
I25: =IF(COUNTA(C25:H25)=0,"",IF(OR(C25="",D25="",E25="",F25="",G25="",H25=""),"INCOMPLETO","CONCLUÍDO"))
I26: =IF(COUNTA(C26:H26)=0,"",IF(OR(C26="",D26="",E26="",F26="",G26="",H26=""),"INCOMPLETO","CONCLUÍDO"))
I27: =IF(COUNTA(C27:H27)=0,"",IF(OR(C27="",D27="",E27="",F27="",G27="",H27=""),"INCOMPLETO","CONCLUÍDO"))
I28: =IF(COUNTA(C28:H28)=0,"",IF(OR(C28="",D28="",E28="",F28="",G28="",H28=""),"INCOMPLETO","CONCLUÍDO"))
I29: =IF(COUNTA(C29:H29)=0,"",IF(OR(C29="",D29="",E29="",F29="",G29="",H29=""),"INCOMPLETO","CONCLUÍDO"))
I30: =IF(COUNTA(C30:H30)=0,"",IF(OR(C30="",D30="",E30="",F30="",G30="",H30=""),"INCOMPLETO","CONCLUÍDO"))
... I50: =IF(COUNTA(C50:H50)=0,"",IF(OR(C50="",D50="",E50="",F50="",G50="",H50=""),"INCOMPLETO","CONCLUÍDO"))

Sheet DOCUMENTOS
C3: 6. CONTROLE DE DOCUMENTOS | I3: =COUNTA(C14:C112) -> 10 | K3: =SUM(#REF!) -> #REF!
C4: Organize os documentos e acompanhe as pendências da declaração do Imposto de Renda. | I4: =COUNTIFS(C14:C112,"<>",F14:F112,"SIM") -> 8 | K4: =SUM(H:H) -> 0
I5: =COUNTIF(H14:H112,"PENDENTE")+COUNTIF(H14:H112,"INCOMPLETO") -> 2 | K5: =COUNTIF(DOCUMENTOS!#REF!,"PENDENTE")+COUNTIF(DOCUMENTOS!#REF!,"INCOMPLETO") -> #REF!
C12: DOCUMENTAÇÃO
C13: DOCUMENTO | D13: CATEGORIA | E13: ANO-CALENDÁRIO | F13: RECEBIDO? | G13: LOCAL DO ARQUIVO | H13: SITUAÇÃO
C14: Documento pessoal | D14: Identificação | E14: 2025 | F14: SIM | G14: identidade.pdf | H14: =IF(COUNTA(C14:G14)=0,"",IF(OR(C14="",D14="",E14="",F14=""),"INCOMPLETO",IF(F14="NÃO","PENDENTE",IF(G14="","INCOMPLETO","CONCLUÍDO")))) -> CONCLUÍDO
C15: Informe bancário | D15: Bancário | E15: 2025 | F15: SIM | G15: banco.pdf | H15: =IF(COUNTA(C15:G15)=0,"",IF(OR(C15="",D15="",E15="",F15=""),"INCOMPLETO",IF(F15="NÃO","PENDENTE",IF(G15="","INCOMPLETO","CONCLUÍDO")))) -> CONCLUÍDO
C16: Informe salarial | D16: Rendimentos | E16: 2025 | F16: SIM | G16: salario.pdf | H16: =IF(COUNTA(C16:G16)=0,"",IF(OR(C16="",D16="",E16="",F16=""),"INCOMPLETO",IF(F16="NÃO","PENDENTE",IF(G16="","INCOMPLETO","CONCLUÍDO")))) -> CONCLUÍDO
C17: Despesas médicas | D17: Pagamentos | E17: 2025 | F17: SIM | G17: saude.pdf | H17: =IF(COUNTA(C17:G17)=0,"",IF(OR(C17="",D17="",E17="",F17=""),"INCOMPLETO",IF(F17="NÃO","PENDENTE",IF(G17="","INCOMPLETO","CONCLUÍDO")))) -> CONCLUÍDO
C18: Despesas escolares | D18: Pagamentos | E18: 2025 | F18: NÃO | H18: =IF(COUNTA(C18:G18)=0,"",IF(OR(C18="",D18="",E18="",F18=""),"INCOMPLETO",IF(F18="NÃO","PENDENTE",IF(G18="","INCOMPLETO","CONCLUÍDO")))) -> PENDENTE
C19: Documento do imóvel | D19: Bens e direitos | E19: 2025 | F19: SIM | G19: imovel.pdf | H19: =IF(COUNTA(C19:G19)=0,"",IF(OR(C19="",D19="",E19="",F19=""),"INCOMPLETO",IF(F19="NÃO","PENDENTE",IF(G19="","INCOMPLETO","CONCLUÍDO")))) -> CONCLUÍDO
C20: Documento do veículo | D20: Bens e direitos | E20: 2025 | F20: SIM | G20: veiculo.pdf | H20: =IF(COUNTA(C20:G20)=0,"",IF(OR(C20="",D20="",E20="",F20=""),"INCOMPLETO",IF(F20="NÃO","PENDENTE",IF(G20="","INCOMPLETO","CONCLUÍDO")))) -> CONCLUÍDO
C21: Informe previdenciário | D21: Pagamentos | E21: 2025 | F21: NÃO | H21: =IF(COUNTA(C21:G21)=0,"",IF(OR(C21="",D21="",E21="",F21=""),"INCOMPLETO",IF(F21="NÃO","PENDENTE",IF(G21="","INCOMPLETO","CONCLUÍDO")))) -> PENDENTE
C22: Documento dependente | D22: Dependentes | E22: 2025 | F22: SIM | G22: dependente.pdf | H22: =IF(COUNTA(C22:G22)=0,"",IF(OR(C22="",D22="",E22="",F22=""),"INCOMPLETO",IF(F22="NÃO","PENDENTE",IF(G22="","INCOMPLETO","CONCLUÍDO")))) -> CONCLUÍDO
C23: Informe investimentos | D23: Rendimentos | E23: 2025 | F23: SIM | G23: investimentos.pdf | H23: =IF(COUNTA(C23:G23)=0,"",IF(OR(C23="",D23="",E23="",F23=""),"INCOMPLETO",IF(F23="NÃO","PENDENTE",IF(G23="","INCOMPLETO","CONCLUÍDO")))) -> CONCLUÍDO
H24: =IF(COUNTA(C24:G24)=0,"",IF(OR(C24="",D24="",E24="",F24=""),"INCOMPLETO",IF(F24="NÃO","PENDENTE",IF(G24="","INCOMPLETO","CONCLUÍDO"))))
H25: =IF(COUNTA(C25:G25)=0,"",IF(OR(C25="",D25="",E25="",F25=""),"INCOMPLETO",IF(F25="NÃO","PENDENTE",IF(G25="","INCOMPLETO","CONCLUÍDO"))))
H26: =IF(COUNTA(C26:G26)=0,"",IF(OR(C26="",D26="",E26="",F26=""),"INCOMPLETO",IF(F26="NÃO","PENDENTE",IF(G26="","INCOMPLETO","CONCLUÍDO"))))
H27: =IF(COUNTA(C27:G27)=0,"",IF(OR(C27="",D27="",E27="",F27=""),"INCOMPLETO",IF(F27="NÃO","PENDENTE",IF(G27="","INCOMPLETO","CONCLUÍDO"))))
H28: =IF(COUNTA(C28:G28)=0,"",IF(OR(C28="",D28="",E28="",F28=""),"INCOMPLETO",IF(F28="NÃO","PENDENTE",IF(G28="","INCOMPLETO","CONCLUÍDO"))))
H29: =IF(COUNTA(C29:G29)=0,"",IF(OR(C29="",D29="",E29="",F29=""),"INCOMPLETO",IF(F29="NÃO","PENDENTE",IF(G29="","INCOMPLETO","CONCLUÍDO"))))
H30: =IF(COUNTA(C30:G30)=0,"",IF(OR(C30="",D30="",E30="",F30=""),"INCOMPLETO",IF(F30="NÃO","PENDENTE",IF(G30="","INCOMPLETO","CONCLUÍDO"))))
H31: =IF(COUNTA(C31:G31)=0,"",IF(OR(C31="",D31="",E31="",F31=""),"INCOMPLETO",IF(F31="NÃO","PENDENTE",IF(G31="","INCOMPLETO","CONCLUÍDO"))))
H32: =IF(COUNTA(C32:G32)=0,"",IF(OR(C32="",D32="",E32="",F32=""),"INCOMPLETO",IF(F32="NÃO","PENDENTE",IF(G32="","INCOMPLETO","CONCLUÍDO"))))
H33: =IF(COUNTA(C33:G33)=0,"",IF(OR(C33="",D33="",E33="",F33=""),"INCOMPLETO",IF(F33="NÃO","PENDENTE",IF(G33="","INCOMPLETO","CONCLUÍDO"))))
H34: =IF(COUNTA(C34:G34)=0,"",IF(OR(C34="",D34="",E34="",F34=""),"INCOMPLETO",IF(F34="NÃO","PENDENTE",IF(G34="","INCOMPLETO","CONCLUÍDO"))))
H35: =IF(COUNTA(C35:G35)=0,"",IF(OR(C35="",D35="",E35="",F35=""),"INCOMPLETO",IF(F35="NÃO","PENDENTE",IF(G35="","INCOMPLETO","CONCLUÍDO"))))
... H51: =IF(COUNTA(C51:G51)=0,"",IF(OR(C51="",D51="",E51="",F51=""),"INCOMPLETO",IF(F51="NÃO","PENDENTE",IF(G51="","INCOMPLETO","CONCLUÍDO"))))

Sheet RESUMO
I2: =SUM(RENDIMENTOS!G:G) -> 27006.3
C3: 7. RESUMO DA DECLARAÇÃO | I3: =SUM(PAGAMENTOS!G:G) -> 7570
C4: Visão consolidada dos valores, documentos e pendências | I4: =SUM('BENS E DIREITOS'!H:H) -> 249500
I5: =BANCOS!F7 -> 25971.35
I6: =COUNTIF(DOCUMENTOS!F14:F112,"SIM")&" de "&COUNTA(DOCUMENTOS!C14:C112) -> 8 de 10
I7: =COUNTIF(BANCOS!D21:D47,"PENDENTE")+COUNTIF(BANCOS!D21:D47,"INCOMPLETO")+COUNTIF(RENDIMENTOS!I:I,"INCOMPLETO")+COUNTIF(PAGAMENTOS!I:I,"INCOMPLETO")+COUNTIF('BENS E DIREITOS'!I:I,"INCOMPLETO")+COUNTIF(DOCUMENTOS!H:H,"PENDENTE")+COUNTIF(DOCUMENTOS!H:H,"INCOMPLETO") -> 6
I11: CATEGORIA | J11: VALOR
I12: Rendimentos | J12: =I2 -> 27006.3
I13: Pagamentos | J13: =I3 -> 7570
I16: SITUAÇÃO | J16: QUANTIDADE
I17: Recebidos | J17: =COUNTIF(DOCUMENTOS!F:F,"SIM") -> 8
I18: Pendentes | J18: =COUNTIF(DOCUMENTOS!F:F,"NÃO") -> 2
I20: ÁREA | J20: TOTAL | K20: PENDÊNCIAS | L20: % CONCLUÍDO
I21: BANCOS | J21: 3 | K21: 2 | L21: =IF(J21=0,0,(J21-K21)/J21) -> 0.33333333 | M21: =1-L21 -> 0.66666667
I22: RENDIMENTOS | J22: 10 | K22: 1 | L22: =IF(J22=0,0,(J22-K22)/J22) -> 0.9 | M22: =1-L22 -> 0.1
I23: PAGAMENTOS | J23: 10 | K23: 0 | L23: =IF(J23=0,0,(J23-K23)/J23) -> 1 | M23: =1-L23 -> 0
I24: BENS E DIREITOS | J24: 5 | K24: 1 | L24: =IF(J24=0,0,(J24-K24)/J24) -> 0.8 | M24: =1-L24 -> 0.2
I25: DOCUMENTOS | J25: 10 | K25: 2 | L25: =IF(J25=0,0,(J25-K25)/J25) -> 0.8 | M25: =1-L25 -> 0.2

Sheet TABELA
C3: 8. TABELAS AUXILIARES
C4: Listas de referência utilizadas nos cadastros e validações do IR Organiza.
C7: BANCOS | D7: TIPOS DE CONTA | E7: TIPOS DE RENDIMENTO | F7: TIPOS DE DESPESA | G7: TIPOS DE BENS | H7: CATEGORIAS DE DOCUMENTOS
C8: 1 - Banco do Brasil | D8: Conta corrente | E8: Salário | F8: Consulta médica | G8: Imóvel | H8: Identificação
C9: 102 - XP Investimentos CCTVM S.A. | D9: Conta poupança | E9: Aposentadoria | F9: Exames | G9: Veículo | H9: Bancário
C10: 104 - Caixa Econômica Federal | D10: Conta de pagamento | E10: Pensão | F10: Dentista | G10: Conta bancária | H10: Rendimentos
C11: 119 - Banco Western Union do Brasil | D11: Conta salário | E11: Aluguel | F11: Psicoterapia | G11: Investimento | H11: Pagamentos
C12: 184 - Banco Itaú BBA S.A. | D12: CDB | E12: Trabalho autônomo | F12: Hospital | G12: Participação societária | H12: Bens e direitos
C13: 197 - Stone Pagamentos | D13: LCI/LCA | E13: Pró-labore | F13: Plano de saúde | G13: Criptoativo | H13: Dependentes
C14: 208 - Banco BTG Pactual | D14: Tesouro Direto | E14: 13º salário | F14: Educação | G14: Outros bens e direitos | H14: Outros
C15: 212 - Banco Original | D15: Fundos de investimento | E15: Juros de aplicações | F15: Previdência privada
C16: 218 - Banco Bonsucesso | D16: Outros | E16: Dividendos | F16: Pensão alimentícia
C17: 229 - Banco Cruzeiro do Sul | E17: Rendimentos de fundos | F17: Outros
C18: 237 - Banco Bradesco | E18: Outros
C19: 24 - Banco de Pernambuco
C20: 241 - Banco Clássico
C21: 250 - Banco de Crédito e Varejo (BCV)
C22: 260 - Nubank
C23: 29 - Banco do Estado do Rio de Janeiro
C24: 290 - PagBank
C25: 3 - Banco da Amazônia
C26: 33 - Banco Santander
C27: 336 - C6 Bank
C28: 341 - Itaú Unibanco
C29: 37 - Banco do Estado do Pará
C30: 376 - Banco JPMorgan S.A.
... C57: 82 - Banco Topázio
